snreval/__init__.py
snreval-1.2.dist-info/LICENSE
snreval-1.2.dist-info/METADATA
snreval-1.2.dist-info/WHEEL
snreval-1.2.dist-info/top_level.txt
snreval-1.2.dist-info/RECORD
