Metadata-Version: 2.1
Name: snreval
Version: 1.2
Summary: This repository provides a small Python wrapper for the Matlab tool SNR Eval provided by Labrosa: https://labrosa.ee.columbia.edu/projects/snreval
Home-page: https://github.com/RemiRigal/snreval-python
Author: Rémi Rigal
Author-email: remi.rigal@ensta-bretagne.org
License: MIT
Platform: UNKNOWN
Requires-Dist: numpy
Requires-Dist: pandas
